[{

    "teamdeatils": {
      "teamName": "Bigweb",
      "memberdetails": {
        "memberName": ["abc", "cdf"]

      }
    }

  },
  {

    "teamdeatils": {
      "teamName": "Mobweb",
      "memberdetails": {
        "memberName": ["abc", "fhj"]

      }
    }
  },
  {

    "teamdeatils": {
      "teamName": "Fnatic",
      "memberdetails": {
        "memberName": ["hhklkmk", "fjhjj"]

      }
    }
  },

  {
      "teamdeatils": {
          "teamName": "Topaz",
          "memberdetails": {
              "memberName":[
                  "Krishna Kumar", "Ankur Bhojak"
              ]
          }
      }
  }

]
